{"unit_id":"sequence","unit_name":"数列","grade":"高校2年","description":"等差数列・等比数列、いろいろな数列の和、漸化式、数学的帰納法までの理解構造（数学B）","nodes":[{"id":"SQ-01","title":"等差数列","description":"等差数列について理解し、一般項や和を求められる","category":"definition","difficulty":2,"prerequisites":[],"tags":["arithmetic","sequence"]},{"id":"SQ-02","title":"等比数列","description":"等比数列について理解し、一般項や和を求められる","category":"definition","difficulty":2,"prerequisites":[],"tags":["geometric","sequence"]},{"id":"SQ-03","title":"いろいろな数列の一般項","description":"いろいろな数列の一般項を求める方法を理解している","category":"operation","difficulty":3,"prerequisites":["SQ-01","SQ-02"],"tags":["general_term"]},{"id":"SQ-04","title":"いろいろな数列の和","description":"Σ を用いた数列の和を求められる","category":"operation","difficulty":3,"prerequisites":["SQ-03"],"tags":["sum","sigma"]},{"id":"SQ-05","title":"漸化式の意味","description":"漸化式について理解し、事象の変化を漸化式で表せる","category":"interpretation","difficulty":3,"prerequisites":["SQ-01","SQ-02"],"tags":["recurrence"]},{"id":"SQ-06","title":"漸化式で表された数列の一般項","description":"簡単な漸化式で表された数列の一般項を求められる","category":"operation","difficulty":4,"prerequisites":["SQ-05"],"tags":["recurrence","general_term"]},{"id":"SQ-07","title":"数学的帰納法","description":"数学的帰納法について理解し、自然数の性質などの証明に用いられる","category":"interpretation","difficulty":4,"prerequisites":["SQ-04"],"tags":["induction","proof"]},{"id":"SQ-08","title":"数列の応用","description":"事象の再帰的な関係に着目し、数列の考えを問題解決に活用できる","category":"application","difficulty":4,"prerequisites":["SQ-06","SQ-07"],"tags":["application"]}]}
